{"Items":[{"DevID":150540,"DetID":41039,"SN":"00023549","Date":"11.11.2013","Address":"ул. Зеленодольская, 10 МГО от съезда с Волгоградского пр-та (дублёр), движение к ул. Шумилова . По правой стороне","Name":"от пр-та Волгоградский - к ул. Шумилова","Lat":55.70808,"Lon":37.76822,"Lanes":3,"PhN":"","SIMCard":"Бокс!","IP":"10.178.36.226","LaneNumbers":"1,2,3","Direction":"right","Angle":"202.08717160322834","Active":"yes","Type":"SMS"},{"DevID":3669,"DetID":10330,"Date":"2012/06/06 00:11:31","Address":"Зеленодольская ул., 6 МГО перед Волгоградским пр-том (дублёр), движение от ул. Юных Ленинцев. По правой стороне","Name":"полоса для общественного транспорта - от ул. Юных Ленинцев - к пр-ту Волгоградский","Lat":55.703583,"Lon":37.766309,"Lanes":1,"PhN":"","SIMCard":"Бокс!","IP":"10.178.43.162","LaneNumbers":"1","Direction":"right","Angle":"285.7320047851073","Active":"yes","Type":"Wavetronix"},{"DevID":3752,"DetID":14171,"Date":"2012/06/07 00:26:59","Address":"Волгоградский пр-т, 9 МГО от Зеленодольской ул., движение в область. По правой стороне","Name":"Волгоградский пр-т - от Зеленодольской ул.","Lat":55.704492,"Lon":37.771681,"Lanes":4,"PhN":"","SIMCard":"Бокс!","IP":"10.178.37.32","LaneNumbers":"1,2,3,4","Direction":"right","Angle":"14.287172284841134","Active":"yes","Type":"Wavetronix"},{"DevID":400654,"DetID":101122,"SN":"000243E0","Date":"01.11.2013","Address":"Волгоградский пр-т, 4 МГО от Есенинского б-ра, движение к ул. Зеленодольская. По правой стороне","Name":"полоса для общественного транспорта - от Есенинского б-ра - к ул. Зеленодольская","Lat":55.704071,"Lon":37.776756,"Lanes":1,"PhN":"","SIMCard":"Бокс!","IP":"10.178.37.56","LaneNumbers":"1","Direction":"right","Angle":"112.77037890876221","Active":"yes","Type":"SMS"},{"DevID":400667,"DetID":101126,"SN":"00023667","Date":"25.11.2013","Address":"Волгоградский пр-т, 9 МГО перед ул. Маршала Чуйкова, движение от Волжского б-ра. По правой стороне","Name":"от Волжского б-ра - к ул. Маршала Чуйкова","Lat":55.706101,"Lon":37.759448,"Lanes":4,"PhN":"","SIMCard":"Бокс!","IP":"10.178.36.248","LaneNumbers":"1,2,3,4","Direction":"right","Angle":"90.0","Active":"yes","Type":"SMS"},{"DevID":430653,"DetID":101122,"SN":"000243E0","Date":"01.11.2013","Address":"Волгоградский пр-т, 4 МГО от Есенинского б-ра, движение к ул. Зеленодольская. По правой стороне","Name":"от Есенинского б-ра - к ул. Зеленодольская","Lat":55.704071,"Lon":37.776756,"Lanes":3,"PhN":"","SIMCard":"Бокс!","IP":"10.178.37.56","LaneNumbers":"2,3,4","Direction":"right","Angle":"112.77037890876221","Active":"yes","Type":"SMS"},{"DevID":6539,"DetID":15385,"Date":"2012/09/29 00:39:13","Address":"Жигулёвская ул., 9 МГО перед Волгоградским пр-том (дублёр), движение от Окской ул. По правой стороне","Name":"от Окской ул. - к Волгоградскому пр-ту","Lat":55.708185,"Lon":37.764589,"Lanes":3,"PhN":"","SIMCard":"Бокс!","IP":"10.178.46.142","LaneNumbers":"1,2,3","Direction":"right","Angle":"66.37062226934319","Active":"yes","Type":"Wavetronix"}],"Total":7,"success":true}